genrator/__init__.py
genrator/genrator.py
genrator/load_and_preprocess_data.py
genrator/main.py
IdentificationOfClaims-0.1.1.dist-info/METADATA
IdentificationOfClaims-0.1.1.dist-info/WHEEL
IdentificationOfClaims-0.1.1.dist-info/top_level.txt
IdentificationOfClaims-0.1.1.dist-info/RECORD
