Metadata-Version: 2.1
Name: IdentificationOfClaims
Version: 0.1.1
Summary: Identifies Claims from Text
Author: Manav
Classifier: Programming Language :: Python :: 3
Classifier: License :: OSI Approved :: MIT License
Classifier: Operating System :: OS Independent
Requires-Python: >=3.6
Requires-Dist: google-generativeai
Requires-Dist: pandas
Requires-Dist: scikit-learn
Requires-Dist: numpy
Requires-Dist: nltk
Requires-Dist: rouge
Requires-Dist: scipy
Requires-Dist: python-dotenv
